logly-0.1.6.dist-info/METADATA
logly-0.1.6.dist-info/WHEEL
logly-0.1.6.dist-info/licenses/LICENSE
logly/__init__.py
logly/_logly.cpython-311-darwin.so
logly/_logly.pyi
logly/py.typed
logly-0.1.6.dist-info/RECORD
