Metadata-Version: 2.4
Name: logly
Version: 0.1.6
Classifier: Development Status :: 4 - Beta
Classifier: Programming Language :: Python :: 3
Classifier: Programming Language :: Python :: 3 :: Only
Classifier: Programming Language :: Python :: 3.10
Classifier: Programming Language :: Python :: 3.11
Classifier: Programming Language :: Python :: 3.12
Classifier: Programming Language :: Python :: 3.13
Classifier: Programming Language :: Python :: 3.14
Classifier: License :: OSI Approved :: MIT License
Classifier: Operating System :: OS Independent
Classifier: Topic :: Software Development :: Libraries :: Python Modules
Classifier: Topic :: System :: Logging
License-File: LICENSE
Summary: A stupidly simple, yet blazingly fast and powerful logging utility for Python — powered by Rust.
Keywords: logging,rust,pyo3,tracing,structured-logging,logly,performance
Author-email: muhammad-fiaz <contact@muhammadfiaz.com>
Maintainer-email: muhammad-fiaz <contact@muhammadfiaz.com>
Requires-Python: >=3.10, <=3.14
Project-URL: Homepage, https://github.com/muhammad-fiaz/logly
Project-URL: Source, https://github.com/muhammad-fiaz/logly
Project-URL: Bug Tracker, https://github.com/muhammad-fiaz/logly/issues
Project-URL: Documentation, https://github.com/muhammad-fiaz/logly#readme
Project-URL: Changelog, https://github.com/muhammad-fiaz/logly/releases
